{"url": "https://www.facebook.com/1003344626383879/posts/1583546611697008/", "created_time": "2017-08-22T01:35:36+0000", "message": "If you can, tune in tomorrow! Alicia is doing wonderful work in Texas! Treasured Vessels Foundation is working to build homes for survivors of human trafficking age 11-17.", "cleaned_message": ["tune", "tomorrow", "alicia", "wonder", "work", "texa", "treasur", "vessel", "foundat", "work", "build", "home", "survivor", "human", "traffick", "age", "-"], "emojis": null, "mentions": null, "names": null, "message_tags": ["Alicia Bush", "Treasured Vessels Foundation"], "attachments": [{"media_type": "photo", "media_url": "https://www.facebook.com/treasuredvesselsfoundation.org/photos/a.756009187838078/1200036560102003/?type=3", "media_description": null, "thumbnail_url": null}], "urls": null, "date": "2017-08-22", "day_week": 1, "Mon": 0, "Tue": 1, "Wed": 0, "Thur": 0, "Fri": 0, "Sat": 0, "winter": 0, "spring": 0, "summer": 1, "hour": 1, "morning": 0, "afternoon": 0, "evening": 0, "share": 0, "share_url": null, "photo": 1, "photo_url": "https://www.facebook.com/treasuredvesselsfoundation.org/photos/a.756009187838078/1200036560102003/?type=3", "video": 0, "video_url": null, "media_desc": [null], "thumbnail_url": [null], "link": 0, "link_url": null, "total engagement": 4, "engagement rate": 20.99737533, "reactions": 3, "shares": 0, "comments": 1}