{"url": "https://www.facebook.com/1003344626383879/posts/1602707393114263/", "created_time": "2017-09-12T23:09:37+0000", "message": "Join us tonight at 8pm for the final part of our 4 part series on Child Empowerment. \n#education", "cleaned_message": ["join", "us", "tonight", "pm", "final", "part", "part", "seri", "child", "empower"], "emojis": null, "mentions": null, "names": null, "message_tags": ["education"], "attachments": null, "urls": null, "date": "2017-09-12", "day_week": 1, "Mon": 0, "Tue": 1, "Wed": 0, "Thur": 0, "Fri": 0, "Sat": 0, "event": 0, "winter": 0, "spring": 0, "summer": 0, "hour": 23, "morning": 0, "afternoon": 0, "evening": 1, "share": 0, "share_url": null, "photo": 0, "photo_url": null, "video": 0, "video_url": null, "media_desc": [], "thumbnail_url": [], "link": 0, "link_url": null, "total_engagement": 2, "engagement_rate": 10.42752868, "reactions": 2, "shares": 0, "comments": 0}