{"url": "https://www.facebook.com/helperase/photos/a.1029649477086727/3344770812241237/?type=3", "created_time": "2020-07-30T22:49:35+0000", "message": "Working alongside dedicated individuals on the front lines in the fight against trafficking is how ERASE makes a difference. We work endlessly to provide victim-centered & trauma-informed services to individuals who have been trafficked. \u2800\n\u201cCommitted to the Cause - Working on the Frontline to End Human Trafficking\u201d\u2800\nThe UN's theme for #WDATIP this year, is to highlight the first responders to human trafficking. These are the people who work in different sectors - identifying, supporting, counseling, and seeking justice for victims of trafficking, and challenging the impunity of the traffickers. \u2800\n#EndHumanTrafficking #HumanTrafficking", "cleaned_message": ["work", "alongsid", "dedic", "individu", "front", "line", "fight", "traffick", "eras", "make", "differ", "work", "endlessli", "provid", "victim-cent", "trauma-inform", "servic", "individu", "traffick", "commit", "caus", "-", "work", "frontlin", "end", "human", "traffick", "un", "theme", "year", "highlight", "first", "respond", "human", "traffick", "peopl", "work", "differ", "sector", "-", "identifi", "support", "counsel", "seek", "justic", "victim", "traffick", "challeng", "impun", "traffick"], "emojis": null, "mentions": null, "names": null, "message_tags": ["WDATiP", "endhumantrafficking", "humantrafficking"], "attachments": [{"media_type": "photo", "media_url": "https://scontent-lax3-2.xx.fbcdn.net/v/t1.0-9/p720x720/116874173_3344770815574570_4464300937057878204_o.jpg?_nc_cat=111&ccb=1-3&_nc_sid=2d5d41&_nc_ohc=NkbGPavOnasAX9FldpO&_nc_ht=scontent-lax3-2.xx&tp=6&oh=2b60da6fa5d0171892aae6142e10514e&oe=606E4D0F", "media_description": null, "thumbnail_url": null}], "urls": null, "original_date": "30 Jul, 2020 18:49", "total_engagement": 29, "engagement_rate": 61.22018155, "reactions": 18, "shares": 11, "comments": 0, "date": "2020-07-30", "day_week": 3, "Mon": 0, "Tue": 0, "Wed": 0, "Thur": 1, "Fri": 0, "Sat": 0, "event": 1, "season": 2, "winter": 0, "spring": 0, "summer": 1, "hour": 18, "time_day": 3, "morning": 0, "afternoon": 0, "evening": 1, "share": 0, "share_url": null, "photo": 1, "photo_url": "https://scontent-lax3-2.xx.fbcdn.net/v/t1.0-9/p720x720/116874173_3344770815574570_4464300937057878204_o.jpg?_nc_cat=111&ccb=1-3&_nc_sid=2d5d41&_nc_ohc=NkbGPavOnasAX9FldpO&_nc_ht=scontent-lax3-2.xx&tp=6&oh=2b60da6fa5d0171892aae6142e10514e&oe=606E4D0F", "video": 0, "video_url": null, "media_desc": null, "thumbnail_url": null, "link": 0, "link_url": null}