{"url": "https://www.facebook.com/helperase/photos/a.1029649477086727/1954443301274002/?type=3", "created_time": "2018-07-29T21:14:20+0000", "message": "#Repost My Refuge House\n\u30fb\u30fb\u30fb\nRaising awareness in preparation for tomorrow, the @unitednations #worlddayagainsttraffickinginpersons on July 30th. \u2b06\ufe0f awareness = \u2b06\ufe0f response-ability. #humantrafficking #endit #endhumantrafficking #globalvillage #helperase", "cleaned_message": ["refug", "hous", "rais", "awar", "prepar", "tomorrow", "juli", "th", "awar", "response-"], "emojis": null, "mentions": ["unitednations"], "names": null, "message_tags": ["My Refuge House", "Repost", "WorldDayAgainstTraffickinginPersons", "humantrafficking", "endit", "endhumantrafficking", "globalvillage", "helpERASE"], "attachments": [{"media_type": "photo", "media_url": "https://www.facebook.com/helperase/photos/a.1029649477086727/1954443301274002/?type=3", "media_description": "Timeline Photos", "thumbnail_url": null}], "urls": null}