{"url": "https://www.facebook.com/1003344626383879/posts/2347148618670133/", "created_time": "2019-04-20T14:04:00+0000", "message": "\u201cif you are arrested for shoplifting four times, it becomes a felony charge. But you can buy and sell a woman as many times as you want and it (was) always a misdemeanor.\u201d Georgia signs in new pimping and pandering legislation.  https://buff.ly/2EjiozS", "cleaned_message": ["arrest", "shoplift", "four", "time", "becom", "feloni", "charg", "buy", "sell", "woman", "mani", "time", "want", "alway", "misdemeanor", "georgia", "sign", "new", "pimp", "pander", "legisl"], "emojis": null, "mentions": null, "names": null, "message_tags": null, "attachments": [{"media_type": "photo", "media_url": "https://scontent-lax3-1.xx.fbcdn.net/v/t1.0-9/57606616_2347148622003466_6493699322704560128_n.jpg?_nc_cat=101&ccb=1-3&_nc_sid=da1649&_nc_ohc=JXc4mK6P0cUAX-kH8h6&_nc_ht=scontent-lax3-1.xx&oh=022edadfa97023d481fde98bb01838b1&oe=6070BDDC", "media_description": null, "thumbnail_url": null}], "urls": ["https://buff.ly/2EjiozS"]}