{"url": "https://www.facebook.com/1003344626383879/posts/2586235304761462/", "created_time": "2019-09-03T23:09:06+0000", "message": null, "cleaned_message": null, "emojis": null, "mentions": null, "names": null, "message_tags": null, "attachments": [{"media_type": "share", "media_url": "https://l.facebook.com/l.php?u=https%3A%2F%2Fbuff.ly%2F2ZJRrA8&h=AT04C6XqCLNECV41nxwHPeGj6-CCmQdO9QdITZ1JMw6Ey8xErT0uNB_aU197rr0RHsBAPGkP_ReTrlug4qsSMtuYlWJMLICm36WNUWNR6SRfaLW_Z07WhuQFpI1wCjFw&s=1", "media_description": "Sheriff's office debuts human trafficking tip website", "thumbnail_url": null}]}