{"url": "https://www.facebook.com/helperase/photos/a.1029649477086727/2464644740253853/?type=3", "created_time": "2019-06-28T14:04:25+0000", "message": "LA County Human Trafficking Task Force needs the public\u2019s help in identifying additional potential victims. -Alleged human trafficker targeted victims on social media, including a 16-year-old with autism. #exploitation #teens #disabilities  #helperase https://buff.ly/2XaszkR", "cleaned_message": ["la", "counti", "human", "traffick", "task", "forc", "need", "public", "help", "identifi", "addit", "potenti", "victim", "-alleg", "human", "traffick", "target", "victim", "social", "media", "includ", "-year-old", "autism"], "emojis": null, "mentions": null, "names": null, "message_tags": ["exploitation", "teens", "Disabilities", "helpERASE"], "attachments": [{"media_type": "photo", "media_url": "https://www.facebook.com/helperase/photos/a.1029649477086727/2464644740253853/?type=3", "media_description": "Timeline Photos", "thumbnail_url": null}], "urls": ["https://buff.ly/2XaszkR"]}