{"url": "https://www.facebook.com/helperase/photos/a.1029649477086727/2556583591059967/?type=3", "created_time": "2019-08-18T14:04:00+0000", "message": "Workshop targets human trafficking - Rocky Mount Telegram #humantrafficking #education #makingadifference https://buff.ly/2NeUqu6", "cleaned_message": ["workshop", "target", "human", "traffick", "-", "rocki", "mount", "telegram"], "emojis": null, "mentions": null, "names": null, "message_tags": ["humantrafficking", "EDUCATION", "makingadifference"], "attachments": [{"media_type": "photo", "media_url": "https://www.facebook.com/helperase/photos/a.1029649477086727/2556583591059967/?type=3", "media_description": "Timeline Photos", "thumbnail_url": null}], "urls": ["https://buff.ly/2NeUqu6"]}