{"created_time": "2020-02-06T18:09:34+0000", "message": "#Missing\n#HelpFindGeorgia\n#pleaseshare", "message_tags": [{"id": "126682420847427", "name": "#missing", "offset": 0, "length": 8}, {"id": "343940432398041", "name": "#helpfindgeorgia", "offset": 9, "length": 16}, {"id": "567507269935706", "name": "#PleaseShare", "offset": 26, "length": 12}], "permalink_url": "https://www.facebook.com/1003344626383879/posts/2915215658530090/", "attachments": {"data": [{"description": "#Missing\n#HelpFindGeorgia\n#pleaseshare", "media": {"image": {"height": 720, "src": "https://scontent-lax3-2.xx.fbcdn.net/v/t1.0-9/p720x720/84248742_2915212351863754_2896441002854187008_o.png?_nc_cat=111&ccb=1-3&_nc_sid=8024bb&_nc_ohc=Mw_Rasv3kTwAX9dBUQz&_nc_ht=scontent-lax3-2.xx&_nc_tp=30&oh=69feba1373b0aceaf63f050f26931d5e&oe=606EBDA6", "width": 720}}, "target": {"id": "2915212345197088", "url": "https://www.facebook.com/helperase/photos/a.1029649477086727/2915212345197088/?type=3"}, "type": "photo", "url": "https://www.facebook.com/helperase/photos/a.1029649477086727/2915212345197088/?type=3"}]}, "id": "1003344626383879_2915215658530090"}