{"created_time": "2018-04-02T03:15:20+0000", "message": "We are always grateful for community and human trafficking advocates to come in and presenting to our law enforcement classes. Thank you Guiding Light Outreach Inc.!", "message_tags": [{"id": "1395307940574644", "name": "Guiding Light Outreach Inc.", "type": "page", "offset": 137, "length": 27}], "permalink_url": "https://www.facebook.com/1003344626383879/posts/1808465322538468/", "attachments": {"data": [{"media": {"image": {"height": 720, "src": "https://scontent-lax3-1.xx.fbcdn.net/v/t1.0-9/s720x720/29433295_1487257678046336_7248260072281735168_n.jpg?_nc_cat=108&ccb=1-3&_nc_sid=110474&_nc_ohc=EnXhFWL7vHMAX-i7a9l&_nc_ht=scontent-lax3-1.xx&tp=7&oh=59f61a76d66adbe2a1e8990f210f0ea1&oe=606F4CB1", "width": 540}}, "subattachments": {"data": [{"media": {"image": {"height": 720, "src": "https://scontent-lax3-1.xx.fbcdn.net/v/t1.0-9/s720x720/29433295_1487257678046336_7248260072281735168_n.jpg?_nc_cat=108&ccb=1-3&_nc_sid=110474&_nc_ohc=EnXhFWL7vHMAX-i7a9l&_nc_ht=scontent-lax3-1.xx&tp=7&oh=59f61a76d66adbe2a1e8990f210f0ea1&oe=606F4CB1", "width": 540}}, "target": {"id": "1487257674713003", "url": "https://www.facebook.com/gloinc.2012/photos/a.1396083463830425/1487257674713003/?type=3"}, "type": "photo", "url": "https://www.facebook.com/gloinc.2012/photos/a.1396083463830425/1487257674713003/?type=3"}, {"media": {"image": {"height": 540, "src": "https://scontent-lax3-1.xx.fbcdn.net/v/t1.0-0/p180x540/29496413_1487257741379663_5810844233250111488_n.jpg?_nc_cat=105&ccb=1-3&_nc_sid=110474&_nc_ohc=QoCtOOUHsRcAX-kXrmZ&_nc_ht=scontent-lax3-1.xx&tp=6&oh=feea843a4acac4c1b42a2d83e50804e4&oe=6071F70F", "width": 720}}, "target": {"id": "1487257738046330", "url": "https://www.facebook.com/gloinc.2012/photos/a.1396083463830425/1487257738046330/?type=3"}, "type": "photo", "url": "https://www.facebook.com/gloinc.2012/photos/a.1396083463830425/1487257738046330/?type=3"}, {"media": {"image": {"height": 720, "src": "https://scontent-lax3-1.xx.fbcdn.net/v/t1.0-9/s720x720/29472871_1487257788046325_8731935290366623744_n.jpg?_nc_cat=103&ccb=1-3&_nc_sid=110474&_nc_ohc=Xo_FgGIyy2wAX_5dWAw&_nc_ht=scontent-lax3-1.xx&tp=7&oh=76dbcf036664ca6e0c5db34cf52a466f&oe=606FC3EE", "width": 540}}, "target": {"id": "1487257784712992", "url": "https://www.facebook.com/gloinc.2012/photos/a.1396083463830425/1487257784712992/?type=3"}, "type": "photo", "url": "https://www.facebook.com/gloinc.2012/photos/a.1396083463830425/1487257784712992/?type=3"}, {"media": {"image": {"height": 720, "src": "https://scontent-lax3-1.xx.fbcdn.net/v/t1.0-9/s720x720/29496396_1487257841379653_3903628069469945856_n.jpg?_nc_cat=109&ccb=1-3&_nc_sid=110474&_nc_ohc=26myH5WXBJYAX_Q_8q2&_nc_ht=scontent-lax3-1.xx&tp=7&oh=b3018219c7e59c1435828e6e5bb27108&oe=6071FA21", "width": 405}}, "target": {"id": "1487257838046320", "url": "https://www.facebook.com/gloinc.2012/photos/a.1396083463830425/1487257838046320/?type=3"}, "type": "photo", "url": "https://www.facebook.com/gloinc.2012/photos/a.1396083463830425/1487257838046320/?type=3"}, {"media": {"image": {"height": 720, "src": "https://scontent-lax3-1.xx.fbcdn.net/v/t1.0-9/s720x720/29468634_1487257908046313_3062413133470498816_n.jpg?_nc_cat=109&ccb=1-3&_nc_sid=110474&_nc_ohc=3Zf34bsgZsgAX8Qaph0&_nc_ht=scontent-lax3-1.xx&tp=7&oh=0a6dd57fedf57cde9fbcad236d54a2f7&oe=6071EB0F", "width": 540}}, "target": {"id": "1487257904712980", "url": "https://www.facebook.com/gloinc.2012/photos/a.1396083463830425/1487257904712980/?type=3"}, "type": "photo", "url": "https://www.facebook.com/gloinc.2012/photos/a.1396083463830425/1487257904712980/?type=3"}]}, "target": {"id": "1487257944712976", "url": "https://www.facebook.com/1395307940574644/posts/1487257944712976/"}, "title": "Photos from Guiding Light Outreach Inc.'s post", "type": "album", "url": "https://www.facebook.com/1395307940574644/posts/1487257944712976/"}]}, "id": "1003344626383879_1808465322538468"}